Workbook

Sheet README
B1: Modern Veil Brand — Financial Model v2
B3: WHAT CHANGED IN V2 | C3: V1 used a single monthly visit growth rate, which made M1-M12 too linear. V2 replaces that with a channel-level Traffic_Ramp tab: Direct/Launch, Organic SEO, Paid Search, TikTok/IG, Pinterest, Creator/Referral, and Other. Monthly_P&L now pulls actual monthly traffic from that ramp.
C4: V2 uses a channel-level Traffic_Ramp tab instead of a single monthly growth rate. The current default assumes a stronger M1 launch push, a small M2 dip, then a ramp toward ~14K monthly visits by M12 as Google Ads, Pinterest, SEO, and collaborations compound.
B5: WHY THIS MATTERS | C5: A cold-start bridal brand does not grow in a smooth line. Launch month can spike, M2 can dip, SEO starts slowly, paid search is budget-controlled, social is lumpy, and creator/referral traffic depends on collaborations. This model is still directional, but it behaves more like a real launch.
B7: HOW TO USE | C7: 1. Assumptions: choose Lean Test / Base Launch / Strong Launch. 2. Traffic_Ramp: edit monthly visits by channel. Blue cells are editable. 3. Monthly_P&L: pulls monthly traffic and scenario assumptions. 4. Scenario_Summary: summarizes the selected traffic ramp under each scenario economics. 5. Launch_Inventory and Marketing_Budget are planning tabs.
B9: IMPORTANT | C9: This is a planning model, not accounting. Replace assumptions with actual Shopify/GA4/Search Console data as soon as the site launches.

Sheet Assumptions
A1: Our Brand — Model Assumptions
A2: Selected scenario → | B2: Base Launch | C2: drives Active column + Monthly_P&L
A3: Scenario index | B3: =MATCH(B2,B5:D5,0)
A5: Driver | B5: Lean Test | C5: Base Launch | D5: Strong Launch | E5: Active | F5: Unit | G5: Notes
A6: Conversion rate | B6: 0.006 | C6: 0.01 | D6: 0.016 | E6: =INDEX(B6:D6,1,$B$3) | F6: % of visits | G6: Cold-start DTC bridal conversion. Improves with product photos, reviews, quiz, swatches.
A7: Average order value (AOV) | B7: 220 | C7: 285 | D7: 340 | E7: =INDEX(B7:D7,1,$B$3) | F7: $/order | G7: Planned veil range ~$149-$429.
A8: COGS (% of net revenue) | B8: 0.3 | C8: 0.24 | D8: 0.2 | E8: =INDEX(B8:D8,1,$B$3) | F8: % net revenue | G8: First batch/small run COGS higher than scaled brand.
A9: Return rate | B9: 0.14 | C9: 0.1 | D9: 0.08 | E9: =INDEX(B9:D9,1,$B$3) | F9: % of gross revenue | G9: No heavy TBYB at launch; swatch/stylist support lowers returns.
A10: Restocking fee per return | B10: 10 | C10: 15 | D10: 15 | E10: =INDEX(B10:D10,1,$B$3) | F10: $/return | G10: Optional policy lever.
A11: Cleaning fee applicable returns | B11: 15 | C11: 20 | D11: 20 | E11: =INDEX(B11:D11,1,$B$3) | F11: $/return | G11: Only if item returned worn/dirty.
A12: % of returns incurring cleaning fee | B12: 0.2 | C12: 0.2 | D12: 0.15 | E12: =INDEX(B12:D12,1,$B$3) | F12: % of returns | G12: Worn/dirty share of returns.
A13: Payment processing | B13: 0.03 | C13: 0.03 | D13: 0.03 | E13: =INDEX(B13:D13,1,$B$3) | F13: % net revenue | G13: Shopify Payments/Stripe-like blended estimate.
A14: Shipping & fulfillment | B14: 12 | C14: 11 | D14: 10 | E14: =INDEX(B14:D14,1,$B$3) | F14: $/gross order | G14: Packaging + fulfillment + shipping subsidy.
A15: Marketing variable spend | B15: 0.18 | C15: 0.22 | D15: 0.26 | E15: =INDEX(B15:D15,1,$B$3) | F15: % net revenue | G15: Variable paid/creator spend after fixed launch budget.
A16: Software & apps monthly | B16: 150 | C16: 300 | D16: 500 | E16: =INDEX(B16:D16,1,$B$3) | F16: $/mo | G16: Shopify, email, reviews, quiz/forms, apps.
A17: Team & labor monthly | B17: 0 | C17: 500 | D17: 1500 | E17: =INDEX(B17:D17,1,$B$3) | F17: $/mo | G17: Founder-led vs contractors/CX.
... A20: Fixed launch SEO/tools setup M1 | B20: 200 | C20: 400 | D20: 800 | E20: =INDEX(B20:D20,1,$B$3) | F20: $ one-time | G20: GSC setup, tools, speed fixes, quiz setup.

Sheet Traffic_Ramp
A1: Traffic Ramp — Nonlinear Channel Plan
A4: Channel | B4: M1 | C4: M2 | D4: M3 | E4: M4 | F4: M5 | G4: M6 | H4: M7 | I4: M8 | J4: M9 | K4: M10 | L4: M11 | M4: M12 | N4: Year 1 | O4: Notes
A5: Direct / launch push | B5: 500 | C5: 120 | D5: 120 | E5: 150 | F5: 180 | G5: 220 | H5: 260 | I5: 300 | J5: 350 | K5: 400 | L5: 450 | M5: 500 | N5: =SUM(B5:M5) | O5: Launch announcement, founder network, direct revisits. M2 can dip after launch.
A6: Organic SEO | B6: 0 | C6: 20 | D6: 60 | E6: 150 | F6: 300 | G6: 600 | H6: 1000 | I6: 1500 | J6: 2200 | K6: 3000 | L6: 3900 | M6: 5000 | N6: =SUM(B6:M6) | O6: SEO is delayed. Impressions first, clicks later.
A7: Google Search Ads | B7: 250 | C7: 300 | D7: 450 | E7: 650 | F7: 800 | G7: 950 | H7: 1100 | I7: 1250 | J7: 1400 | K7: 1500 | L7: 1600 | M7: 1700 | N7: =SUM(B7:M7) | O7: Budget-controlled high-intent keyword testing.
A8: TikTok / Instagram organic | B8: 250 | C8: 180 | D8: 350 | E8: 450 | F8: 650 | G8: 700 | H8: 900 | I8: 1000 | J8: 1200 | K8: 1300 | L8: 1450 | M8: 1500 | N8: =SUM(B8:M8) | O8: Lumpy content performance, not linear.
A9: Pinterest | B9: 30 | C9: 70 | D9: 150 | E9: 300 | F9: 550 | G9: 900 | H9: 1300 | I9: 1800 | J9: 2300 | K9: 2800 | L9: 3300 | M9: 3800 | N9: =SUM(B9:M9) | O9: Visual search grows gradually after pin volume builds.
A10: Creator / photographer referrals | B10: 130 | C10: 170 | D10: 200 | E10: 400 | F10: 600 | G10: 850 | H10: 1200 | I10: 1500 | J10: 1800 | K10: 2000 | L10: 1700 | M10: 1300 | N10: =SUM(B10:M10) | O10: Depends on collaborations, shoots, backlinks, tags.
A11: Other / email / PR | B11: 40 | C11: 40 | D11: 70 | E11: 100 | F11: 220 | G11: 580 | H11: 540 | I11: 550 | J11: 450 | K11: 300 | L11: 300 | M11: 200 | N11: =SUM(B11:M11) | O11: Small miscellaneous sources.
A12: Total visits | B12: =SUM(B5:B11) | C12: =SUM(C5:C11) | D12: =SUM(D5:D11) | E12: =SUM(E5:E11) | F12: =SUM(F5:F11) | G12: =SUM(G5:G11) | H12: =SUM(H5:H11) | I12: =SUM(I5:I11) | ... N12: =SUM(N5:N11) | O12: Monthly_P&L pulls this row.

Sheet Monthly_P&L
A1: Our Brand — Year 1 Monthly P&L
A2: ="Selected scenario: "&Assumptions!B2
A4: Line ($ unless noted) | B4: M1 | C4: M2 | D4: M3 | E4: M4 | F4: M5 | G4: M6 | H4: M7 | I4: M8 | J4: M9 | K4: M10 | L4: M11 | M4: M12 | N4: Year 1
A5: Visits | B5: =Traffic_Ramp!B12 | C5: =Traffic_Ramp!C12 | D5: =Traffic_Ramp!D12 | E5: =Traffic_Ramp!E12 | F5: =Traffic_Ramp!F12 | G5: =Traffic_Ramp!G12 | H5: =Traffic_Ramp!H12 | I5: =Traffic_Ramp!I12 | ... M5: =Traffic_Ramp!M12 | N5: =SUM(B5:M5)
A6: Conversion rate | B6: =Assumptions!$E$6 | C6: =Assumptions!$E$6 | D6: =Assumptions!$E$6 | E6: =Assumptions!$E$6 | F6: =Assumptions!$E$6 | G6: =Assumptions!$E$6 | H6: =Assumptions!$E$6 | I6: =Assumptions!$E$6 | ... M6: =Assumptions!$E$6 | N6: =IFERROR(N7/N5,0)
A7: Orders | B7: =B5*B6 | C7: =C5*C6 | D7: =D5*D6 | E7: =E5*E6 | F7: =F5*F6 | G7: =G5*G6 | H7: =H5*H6 | I7: =I5*I6 | ... M7: =M5*M6 | N7: =SUM(B7:M7)
A8: AOV ($) | B8: =Assumptions!$E$7 | C8: =Assumptions!$E$7 | D8: =Assumptions!$E$7 | E8: =Assumptions!$E$7 | F8: =Assumptions!$E$7 | G8: =Assumptions!$E$7 | H8: =Assumptions!$E$7 | I8: =Assumptions!$E$7 | ... M8: =Assumptions!$E$7 | N8: =IFERROR(N9/N7,0)
A9: Gross revenue | B9: =B7*B8 | C9: =C7*C8 | D9: =D7*D8 | E9: =E7*E8 | F9: =F7*F8 | G9: =G7*G8 | H9: =H7*H8 | I9: =I7*I8 | ... M9: =M7*M8 | N9: =SUM(B9:M9)
A10: Less: returns | B10: =-B9*Assumptions!$E$9 | C10: =-C9*Assumptions!$E$9 | D10: =-D9*Assumptions!$E$9 | E10: =-E9*Assumptions!$E$9 | F10: =-F9*Assumptions!$E$9 | G10: =-G9*Assumptions!$E$9 | H10: =-H9*Assumptions!$E$9 | I10: =-I9*Assumptions!$E$9 | ... M10: =-M9*Assumptions!$E$9 | N10: =SUM(B10:M10)
A11: Net revenue (kept) | B11: =B9+B10 | C11: =C9+C10 | D11: =D9+D10 | E11: =E9+E10 | F11: =F9+F10 | G11: =G9+G10 | H11: =H9+H10 | I11: =I9+I10 | ... M11: =M9+M10 | N11: =SUM(B11:M11)
A12: Restocking fee income | B12: =B7*Assumptions!$E$9*Assumptions!$E$10 | C12: =C7*Assumptions!$E$9*Assumptions!$E$10 | D12: =D7*Assumptions!$E$9*Assumptions!$E$10 | E12: =E7*Assumptions!$E$9*Assumptions!$E$10 | F12: =F7*Assumptions!$E$9*Assumptions!$E$10 | G12: =G7*Assumptions!$E$9*Assumptions!$E$10 | H12: =H7*Assumptions!$E$9*Assumptions!$E$10 | I12: =I7*Assumptions!$E$9*Assumptions!$E$10 | ... M12: =M7*Assumptions!$E$9*Assumptions!$E$10 | N12: =SUM(B12:M12)
A13: Cleaning fee income | B13: =B7*Assumptions!$E$9*Assumptions!$E$12*Assumptions!$E$11 | C13: =C7*Assumptions!$E$9*Assumptions!$E$12*Assumptions!$E$11 | D13: =D7*Assumptions!$E$9*Assumptions!$E$12*Assumptions!$E$11 | E13: =E7*Assumptions!$E$9*Assumptions!$E$12*Assumptions!$E$11 | F13: =F7*Assumptions!$E$9*Assumptions!$E$12*Assumptions!$E$11 | G13: =G7*Assumptions!$E$9*Assumptions!$E$12*Assumptions!$E$11 | H13: =H7*Assumptions!$E$9*Assumptions!$E$12*Assumptions!$E$11 | I13: =I7*Assumptions!$E$9*Assumptions!$E$12*Assumptions!$E$11 | ... M13: =M7*Assumptions!$E$9*Assumptions!$E$12*Assumptions!$E$11 | N13: =SUM(B13:M13)
A14: Total revenue | B14: =B11+B12+B13 | C14: =C11+C12+C13 | D14: =D11+D12+D13 | E14: =E11+E12+E13 | F14: =F11+F12+F13 | G14: =G11+G12+G13 | H14: =H11+H12+H13 | I14: =I11+I12+I13 | ... M14: =M11+M12+M13 | N14: =SUM(B14:M14)
A15: COGS | B15: =-B11*Assumptions!$E$8 | C15: =-C11*Assumptions!$E$8 | D15: =-D11*Assumptions!$E$8 | E15: =-E11*Assumptions!$E$8 | F15: =-F11*Assumptions!$E$8 | G15: =-G11*Assumptions!$E$8 | H15: =-H11*Assumptions!$E$8 | I15: =-I11*Assumptions!$E$8 | ... M15: =-M11*Assumptions!$E$8 | N15: =SUM(B15:M15)
A16: Gross profit | B16: =B14+B15 | C16: =C14+C15 | D16: =D14+D15 | E16: =E14+E15 | F16: =F14+F15 | G16: =G14+G15 | H16: =H14+H15 | I16: =I14+I15 | ... M16: =M14+M15 | N16: =SUM(B16:M16)
A17: Gross margin % | B17: =IFERROR(B16/B14,0) | C17: =IFERROR(C16/C14,0) | D17: =IFERROR(D16/D14,0) | E17: =IFERROR(E16/E14,0) | F17: =IFERROR(F16/F14,0) | G17: =IFERROR(G16/G14,0) | H17: =IFERROR(H16/H14,0) | I17: =IFERROR(I16/I14,0) | ... N17: =IFERROR(N16/N14,0)
A19: Payment processing | B19: =-B11*Assumptions!$E$13 | C19: =-C11*Assumptions!$E$13 | D19: =-D11*Assumptions!$E$13 | E19: =-E11*Assumptions!$E$13 | F19: =-F11*Assumptions!$E$13 | G19: =-G11*Assumptions!$E$13 | H19: =-H11*Assumptions!$E$13 | I19: =-I11*Assumptions!$E$13 | ... M19: =-M11*Assumptions!$E$13 | N19: =SUM(B19:M19)
A20: Shipping & fulfillment | B20: =-B7*Assumptions!$E$14 | C20: =-C7*Assumptions!$E$14 | D20: =-D7*Assumptions!$E$14 | E20: =-E7*Assumptions!$E$14 | F20: =-F7*Assumptions!$E$14 | G20: =-G7*Assumptions!$E$14 | H20: =-H7*Assumptions!$E$14 | I20: =-I7*Assumptions!$E$14 | ... M20: =-M7*Assumptions!$E$14 | N20: =SUM(B20:M20)
A21: Marketing variable spend | B21: =-B11*Assumptions!$E$15 | C21: =-C11*Assumptions!$E$15 | D21: =-D11*Assumptions!$E$15 | E21: =-E11*Assumptions!$E$15 | F21: =-F11*Assumptions!$E$15 | G21: =-G11*Assumptions!$E$15 | H21: =-H11*Assumptions!$E$15 | I21: =-I11*Assumptions!$E$15 | ... M21: =-M11*Assumptions!$E$15 | N21: =SUM(B21:M21)
A22: Contribution margin | B22: =B16+B19+B20+B21 | C22: =C16+C19+C20+C21 | D22: =D16+D19+D20+D21 | E22: =E16+E19+E20+E21 | F22: =F16+F19+F20+F21 | G22: =G16+G19+G20+G21 | H22: =H16+H19+H20+H21 | I22: =I16+I19+I20+I21 | ... M22: =M16+M19+M20+M21 | N22: =SUM(B22:M22)
A23: Contribution margin % | B23: =IFERROR(B22/B14,0) | C23: =IFERROR(C22/C14,0) | D23: =IFERROR(D22/D14,0) | E23: =IFERROR(E22/E14,0) | F23: =IFERROR(F22/F14,0) | G23: =IFERROR(G22/G14,0) | H23: =IFERROR(H22/H14,0) | I23: =IFERROR(I22/I14,0) | ... N23: =IFERROR(N22/N14,0)
A25: Software & apps | B25: =-Assumptions!$E$16 | C25: =-Assumptions!$E$16 | D25: =-Assumptions!$E$16 | E25: =-Assumptions!$E$16 | F25: =-Assumptions!$E$16 | G25: =-Assumptions!$E$16 | H25: =-Assumptions!$E$16 | I25: =-Assumptions!$E$16 | ... M25: =-Assumptions!$E$16 | N25: =SUM(B25:M25)
A26: Team & labor | B26: =-Assumptions!$E$17 | C26: =-Assumptions!$E$17 | D26: =-Assumptions!$E$17 | E26: =-Assumptions!$E$17 | F26: =-Assumptions!$E$17 | G26: =-Assumptions!$E$17 | H26: =-Assumptions!$E$17 | I26: =-Assumptions!$E$17 | ... M26: =-Assumptions!$E$17 | N26: =SUM(B26:M26)
A27: Other overhead | B27: =-Assumptions!$E$18 | C27: =-Assumptions!$E$18 | D27: =-Assumptions!$E$18 | E27: =-Assumptions!$E$18 | F27: =-Assumptions!$E$18 | G27: =-Assumptions!$E$18 | H27: =-Assumptions!$E$18 | I27: =-Assumptions!$E$18 | ... M27: =-Assumptions!$E$18 | N27: =SUM(B27:M27)
A28: Fixed launch content budget | B28: =IF(B$4="M1",-Assumptions!$E$19,0) | C28: =IF(C$4="M1",-Assumptions!$E$19,0) | D28: =IF(D$4="M1",-Assumptions!$E$19,0) | E28: =IF(E$4="M1",-Assumptions!$E$19,0) | F28: =IF(F$4="M1",-Assumptions!$E$19,0) | G28: =IF(G$4="M1",-Assumptions!$E$19,0) | H28: =IF(H$4="M1",-Assumptions!$E$19,0) | I28: =IF(I$4="M1",-Assumptions!$E$19,0) | ... M28: =IF(M$4="M1",-Assumptions!$E$19,0) | N28: =SUM(B28:M28)
A29: Fixed launch SEO/tools setup | B29: =IF(B$4="M1",-Assumptions!$E$20,0) | C29: =IF(C$4="M1",-Assumptions!$E$20,0) | D29: =IF(D$4="M1",-Assumptions!$E$20,0) | E29: =IF(E$4="M1",-Assumptions!$E$20,0) | F29: =IF(F$4="M1",-Assumptions!$E$20,0) | G29: =IF(G$4="M1",-Assumptions!$E$20,0) | H29: =IF(H$4="M1",-Assumptions!$E$20,0) | I29: =IF(I$4="M1",-Assumptions!$E$20,0) | ... M29: =IF(M$4="M1",-Assumptions!$E$20,0) | N29: =SUM(B29:M29)
A30: Operating profit (EBITDA) | B30: =B22+B25+B26+B27+B28+B29 | C30: =C22+C25+C26+C27+C28+C29 | D30: =D22+D25+D26+D27+D28+D29 | E30: =E22+E25+E26+E27+E28+E29 | F30: =F22+F25+F26+F27+F28+F29 | G30: =G22+G25+G26+G27+G28+G29 | H30: =H22+H25+H26+H27+H28+H29 | I30: =I22+I25+I26+I27+I28+I29 | ... M30: =M22+M25+M26+M27+M28+M29 | N30: =SUM(B30:M30)
A31: Operating margin % | B31: =IFERROR(B30/B14,0) | C31: =IFERROR(C30/C14,0) | D31: =IFERROR(D30/D14,0) | E31: =IFERROR(E30/E14,0) | F31: =IFERROR(F30/F14,0) | G31: =IFERROR(G30/G14,0) | H31: =IFERROR(H30/H14,0) | I31: =IFERROR(I30/I14,0) | ... N31: =IFERROR(N30/N14,0)
A32: Break-even revenue needed | B32: =IFERROR(-(B25+B26+B27+B28+B29)/B23,0) | C32: =IFERROR(-(C25+C26+C27+C28+C29)/C23,0) | D32: =IFERROR(-(D25+D26+D27+D28+D29)/D23,0) | E32: =IFERROR(-(E25+E26+E27+E28+E29)/E23,0) | F32: =IFERROR(-(F25+F26+F27+F28+F29)/F23,0) | G32: =IFERROR(-(G25+G26+G27+G28+G29)/G23,0) | H32: =IFERROR(-(H25+H26+H27+H28+H29)/H23,0) | I32: =IFERROR(-(I25+I26+I27+I28+I29)/I23,0) | ... M32: =IFERROR(-(M25+M26+M27+M28+M29)/M23,0) | N32: =AVERAGE(B32:M32)

Sheet Scenario_Summary
A1: Our Brand — Year 1 Scenario Comparison
A2: Same nonlinear Traffic_Ramp, different scenario economics from Assumptions.
A4: Year 1 ($ unless noted) | B4: Lean Test | C4: Base Launch | D4: Strong Launch | E4: How to read
A5: Visits | B5: =Traffic_Ramp!N12 | C5: =Traffic_Ramp!N12 | D5: =Traffic_Ramp!N12 | E5: Traffic_Ramp total visits
A6: Orders | B6: =B5*Assumptions!B6 | C6: =C5*Assumptions!C6 | D6: =D5*Assumptions!D6 | E6: Visits x conversion rate
A7: Gross revenue | B7: =B6*Assumptions!B7 | C7: =C6*Assumptions!C7 | D7: =D6*Assumptions!D7 | E7: Before returns
A8: Less: returns | B8: =-B7*Assumptions!B9 | C8: =-C7*Assumptions!C9 | D8: =-D7*Assumptions!D9 | E8: Revenue refunded
A9: Net revenue (kept) | B9: =B7+B8 | C9: =C7+C8 | D9: =D7+D8 | E9: Core kept product revenue
A10: Fee income | B10: =B6*Assumptions!B9*Assumptions!B10+B6*Assumptions!B9*Assumptions!B12*Assumptions!B11 | C10: =C6*Assumptions!C9*Assumptions!C10+C6*Assumptions!C9*Assumptions!C12*Assumptions!C11 | D10: =D6*Assumptions!D9*Assumptions!D10+D6*Assumptions!D9*Assumptions!D12*Assumptions!D11 | E10: Restocking/cleaning offsets
A11: Total revenue | B11: =B9+B10 | C11: =C9+C10 | D11: =D9+D10 | E11: Net revenue + fee income
A12: COGS | B12: =-B9*Assumptions!B8 | C12: =-C9*Assumptions!C8 | D12: =-D9*Assumptions!D8 | E12: Product cost on kept revenue
A13: Gross profit | B13: =B11+B12 | C13: =C11+C12 | D13: =D11+D12 | E13: Before channel and ops costs
A14: Gross margin % | B14: =IFERROR(B13/B11,0) | C14: =IFERROR(C13/C11,0) | D14: =IFERROR(D13/D11,0) | E14: Product economics health
A15: Marketing variable spend | B15: =-B9*Assumptions!B15 | C15: =-C9*Assumptions!C15 | D15: =-D9*Assumptions!D15 | E15: Paid/creator spend tied to revenue
A16: Contribution margin | B16: =B13+B15-B9*Assumptions!B13-B6*Assumptions!B14 | C16: =C13+C15-C9*Assumptions!C13-C6*Assumptions!C14 | D16: =D13+D15-D9*Assumptions!D13-D6*Assumptions!D14 | E16: After variable costs
A17: Contribution margin % | B17: =IFERROR(B16/B11,0) | C17: =IFERROR(C16/C11,0) | D17: =IFERROR(D16/D11,0) | E17: Can this scale?
A18: Fixed operating costs | B18: =-(Assumptions!B16+Assumptions!B17+Assumptions!B18)*12-Assumptions!B19-Assumptions!B20 | C18: =-(Assumptions!C16+Assumptions!C17+Assumptions!C18)*12-Assumptions!C19-Assumptions!C20 | D18: =-(Assumptions!D16+Assumptions!D17+Assumptions!D18)*12-Assumptions!D19-Assumptions!D20 | E18: Software/team/overhead/content/setup
A19: Operating profit (EBITDA) | B19: =B16+B18 | C19: =C16+C18 | D19: =D16+D18 | E19: Year 1 directional profit
A20: Operating margin % | B20: =IFERROR(B19/B11,0) | C20: =IFERROR(C19/C11,0) | D20: =IFERROR(D19/D11,0) | E20: Profitability after modeled spend
A21: Avg monthly revenue | B21: =B11/12 | C21: =C11/12 | D21: =D11/12 | E21: Annual revenue / 12
A22: Marketing $/order | B22: =IFERROR(-B15/B6,0) | C22: =IFERROR(-C15/C6,0) | D22: =IFERROR(-D15/D6,0) | E22: Variable marketing efficiency

Sheet Launch_Inventory
A1: Launch Inventory — First 100 Veils
A4: SKU | B4: Units | C4: Retail price | D4: Landed COGS/unit | E4: Inventory cost | F4: Retail value | G4: Notes
A5: Minimal Cathedral / Barely-There Long Veil | B5: 27 | C5: 229 | D5: 48 | E5: =B5*D5 | F5: =B5*C5 | G5: SEO foundation: cathedral veil + long wedding veil
A6: Soft Pearl Long Veil | B6: 20 | C6: 299 | D6: 62 | E6: =B6*D6 | F6: =B6*C6 | G6: Strong upgrade SKU; pearl veil / satin dress angle
A7: Modern Mantilla Veil | B7: 12 | C7: 379 | D7: 78 | E7: =B7*D7 | F7: =B7*C7 | G7: Raised due to Keyword Planner: mantilla veil high-volume
A8: Soft Lace Long Veil | B8: 11 | C8: 349 | D8: 72 | E8: =B8*D8 | F8: =B8*C8 | G8: lace veil / lace cathedral veil
A9: Structured Long Veil | B9: 11 | C9: 299 | D9: 58 | E9: =B9*D9 | F9: =B9*C9 | G9: modern/horsehair differentiation
A10: Second Look Blusher Veil | B10: 9 | C10: 179 | D10: 36 | E10: =B10*D10 | F10: =B10*C10 | G10: short veil / blusher / city hall
A11: Garden Long Veil | B11: 5 | C11: 399 | D11: 95 | E11: =B11*D11 | F11: =B11*C11 | G11: visual/content test
A12: Candlelight Veil | B12: 5 | C12: 379 | D12: 90 | E12: =B12*D12 | F12: =B12*C12 | G12: glam/content test
A14: Total | B14: =SUM(B5:B12) | C14: =SUM(C5:C12) | D14: =SUM(D5:D12) | E14: =SUM(E5:E12) | F14: =SUM(F5:F12)

Sheet Marketing_Budget
A1: First 3 Months Marketing Budget
A4: Channel / Spend Area | B4: Lean Test | C4: Base Launch | D4: Strong Launch | E4: Primary KPI | F4: Why it matters
A5: Content shooting / UGC / product assets | B5: 500 | C5: 1200 | D5: 2500 | E5: usable assets | F5: Needed before ads and conversion.
A6: Google Search Ads keyword test | B6: 400 | C6: 900 | D6: 1800 | E6: CPC, CTR, add-to-cart | F6: Fast validation for cathedral veil, mantilla veil, pearl veil.
A7: Creator / photographer / stylist collaborations | B7: 300 | C7: 700 | D7: 1400 | E7: UGC, backlinks, saves | F7: Gets credible visuals, industry links, social proof.
A8: TikTok / Meta amplification | B8: 150 | C8: 350 | D8: 800 | E8: hook CTR, video holds | F8: Only boost content that already performs organically.
A9: Pinterest creative / scheduling | B9: 75 | C9: 150 | D9: 300 | E9: saves, outbound clicks | F9: Bridal planning discovery and visual search.
A10: Tools / quiz / email setup | B10: 125 | C10: 300 | D10: 600 | E10: email signups, quiz starts | F10: Captures demand before SEO matures.
A12: Total first 3 months | B12: =SUM(B5:B10) | C12: =SUM(C5:C10) | D12: =SUM(D5:D10)

Sheet SEO_KPI_Tracker
A1: SEO KPI Tracker — First 6 Months
A4: Metric | B4: M1 | C4: M2 | D4: M3 | E4: M4 | F4: M5 | G4: M6 | H4: Notes
A5: Indexed pages | B5: 10 | C5: 18 | D5: 25 | E5: 35 | F5: 45 | G5: 60 | H5: GSC index coverage.
A6: Organic impressions | B6: 0 | C6: 100 | D6: 500 | E6: 1500 | F6: 3500 | G6: 7000 | H6: Leading indicator.
A7: Organic clicks | B7: 0 | C7: 5 | D7: 20 | E7: 60 | F7: 140 | G7: 300 | H7: Clicks lag impressions.
A8: Top 20 keyword count | B8: 0 | C8: 0 | D8: 2 | E8: 5 | F8: 10 | G8: 18 | H8: Cathedral/mantilla/guide terms.
A9: Email signups from SEO/content | B9: 0 | C9: 5 | D9: 15 | E9: 35 | F9: 70 | G9: 120 | H9: Captures users before purchase.
A10: Swatch/quiz starts | B10: 0 | C10: 5 | D10: 20 | E10: 45 | F10: 90 | G10: 150 | H10: Measures trust and selection intent.
